kinCoke/__init__.py
kinCoke-0.0.2.dist-info/LICENCE
kinCoke-0.0.2.dist-info/METADATA
kinCoke-0.0.2.dist-info/WHEEL
kinCoke-0.0.2.dist-info/top_level.txt
kinCoke-0.0.2.dist-info/RECORD
